YitaiFangGuanwangWendangZhongwenban/README.md
YitaiFangGuanwangWendangZhongwenban/__init__.py
YitaiFangGuanwangWendangZhongwenban/__main__.py
YitaiFangGuanwangWendangZhongwenban/file.epub
YitaiFangGuanwangWendangZhongwenban/index.html
YitaiFangGuanwangWendangZhongwenban/css/__init__.py
YitaiFangGuanwangWendangZhongwenban/css/annotations.css
YitaiFangGuanwangWendangZhongwenban/css/main.css
YitaiFangGuanwangWendangZhongwenban/css/normalize.css
YitaiFangGuanwangWendangZhongwenban/css/popup.css
YitaiFangGuanwangWendangZhongwenban/font/__init__.py
YitaiFangGuanwangWendangZhongwenban/font/fontello.eot
YitaiFangGuanwangWendangZhongwenban/font/fontello.svg
YitaiFangGuanwangWendangZhongwenban/font/fontello.ttf
YitaiFangGuanwangWendangZhongwenban/font/fontello.woff
YitaiFangGuanwangWendangZhongwenban/img/__init__.py
YitaiFangGuanwangWendangZhongwenban/img/annotator-glyph-sprite.png
YitaiFangGuanwangWendangZhongwenban/img/annotator-icon-sprite.png
YitaiFangGuanwangWendangZhongwenban/img/apple-touch-icon.png
YitaiFangGuanwangWendangZhongwenban/img/cancelfullscreen.png
YitaiFangGuanwangWendangZhongwenban/img/close.png
YitaiFangGuanwangWendangZhongwenban/img/fullscreen.png
YitaiFangGuanwangWendangZhongwenban/img/loader.gif
YitaiFangGuanwangWendangZhongwenban/img/menu-icon.png
YitaiFangGuanwangWendangZhongwenban/img/save.png
YitaiFangGuanwangWendangZhongwenban/img/saved.png
YitaiFangGuanwangWendangZhongwenban/img/settings-s.png
YitaiFangGuanwangWendangZhongwenban/img/settings.png
YitaiFangGuanwangWendangZhongwenban/img/star.png
YitaiFangGuanwangWendangZhongwenban/js/__init__.py
YitaiFangGuanwangWendangZhongwenban/js/epub.js
YitaiFangGuanwangWendangZhongwenban/js/epub.min.js
YitaiFangGuanwangWendangZhongwenban/js/epub.min.map
YitaiFangGuanwangWendangZhongwenban/js/hooks.min.js
YitaiFangGuanwangWendangZhongwenban/js/hooks.min.map
YitaiFangGuanwangWendangZhongwenban/js/reader.js
YitaiFangGuanwangWendangZhongwenban/js/reader.js.map
YitaiFangGuanwangWendangZhongwenban/js/reader.min.js
yitai_fang_guanwang_wendang_zhongwenban-2024.3.3.0.dist-info/METADATA
yitai_fang_guanwang_wendang_zhongwenban-2024.3.3.0.dist-info/WHEEL
yitai_fang_guanwang_wendang_zhongwenban-2024.3.3.0.dist-info/entry_points.txt
yitai_fang_guanwang_wendang_zhongwenban-2024.3.3.0.dist-info/top_level.txt
yitai_fang_guanwang_wendang_zhongwenban-2024.3.3.0.dist-info/RECORD
